earthsearch/__init__.py
earthsearch/chip.py
earthsearch/cli.py
earthsearch/core.py
earthsearch/index.py
earthsearch/search.py
earthsearch-0.1.5.dist-info/LICENSE
earthsearch-0.1.5.dist-info/METADATA
earthsearch-0.1.5.dist-info/WHEEL
earthsearch-0.1.5.dist-info/entry_points.txt
earthsearch-0.1.5.dist-info/top_level.txt
earthsearch-0.1.5.dist-info/RECORD
