Metadata-Version: 2.2
Name: earthsearch
Version: 0.1.5
Summary: A library for efficient indexing & similarity search of satellite images.
Author-email: Andrew Ryan <andrewryan@duck.com>
License: MIT
Project-URL: Homepage, https://github.com/andreweryan/earthsearch
Project-URL: Bug Tracker, https://github.com/andreweryan/earthsearch/issues
Project-URL: Source Code, https://github.com/andreweryan/earthsearch
Keywords: geospatial,similarity,indexing,satellite imagery
Requires-Python: >=3.12
License-File: LICENSE
